odoo/addons/stock_available_portal/README.rst
odoo/addons/stock_available_portal/__init__.py
odoo/addons/stock_available_portal/__manifest__.py
odoo/addons/stock_available_portal/controllers/__init__.py
odoo/addons/stock_available_portal/controllers/portal.py
odoo/addons/stock_available_portal/i18n/it.po
odoo/addons/stock_available_portal/i18n/stock_available_portal.pot
odoo/addons/stock_available_portal/models/__init__.py
odoo/addons/stock_available_portal/models/product_product.py
odoo/addons/stock_available_portal/models/res_config_settings.py
odoo/addons/stock_available_portal/readme/CONFIGURE.rst
odoo/addons/stock_available_portal/readme/CONTRIBUTORS.rst
odoo/addons/stock_available_portal/readme/DESCRIPTION.rst
odoo/addons/stock_available_portal/readme/USAGE.rst
odoo/addons/stock_available_portal/static/description/icon.png
odoo/addons/stock_available_portal/static/description/index.html
odoo/addons/stock_available_portal/tests/__init__.py
odoo/addons/stock_available_portal/tests/test_portal_product.py
odoo/addons/stock_available_portal/tests/test_product_product.py
odoo/addons/stock_available_portal/views/product_portal_templates.xml
odoo/addons/stock_available_portal/views/res_config_settings_views.xml
odoo14_addon_stock_available_portal-14.0.1.0.1.dev6.dist-info/METADATA
odoo14_addon_stock_available_portal-14.0.1.0.1.dev6.dist-info/WHEEL
odoo14_addon_stock_available_portal-14.0.1.0.1.dev6.dist-info/top_level.txt
odoo14_addon_stock_available_portal-14.0.1.0.1.dev6.dist-info/RECORD
